bgcar/__init__.py
bgcar/cli.py
bgcar-1.0.2.dist-info/LICENSE
bgcar-1.0.2.dist-info/METADATA
bgcar-1.0.2.dist-info/WHEEL
bgcar-1.0.2.dist-info/entry_points.txt
bgcar-1.0.2.dist-info/top_level.txt
bgcar-1.0.2.dist-info/RECORD
