Metadata-Version: 2.1
Name: bgcar
Version: 1.0.2
Summary: Baldur's Gate Computer Assisted Reroll for easy character high ability scores roll
Home-page: https://github.com/simonkeyd/bgcar
Author: simonkeyd
Author-email: simon.kheng1337@gmail.com
License: GNU GPLv3
Classifier: Programming Language :: Python :: 3
Classifier: License :: OSI Approved :: GNU General Public License v3 (GPLv3)
Classifier: Operating System :: OS Independent
Requires-Python: >=3.4
License-File: LICENSE
Requires-Dist: numpy
Requires-Dist: pynput
Requires-Dist: easyocr
Requires-Dist: rich
Requires-Dist: pillow >=7.1.0
